MANIFEST.in
README.rst
setup.py
docs/CONTRIBUTORS.rst
docs/HISTORY.rst
docs/LICENSE.GPL
docs/LICENSE.txt
seantis/.DS_Store
seantis/__init__.py
seantis.cover.people.egg-info/PKG-INFO
seantis.cover.people.egg-info/SOURCES.txt
seantis.cover.people.egg-info/dependency_links.txt
seantis.cover.people.egg-info/entry_points.txt
seantis.cover.people.egg-info/namespace_packages.txt
seantis.cover.people.egg-info/not-zip-safe
seantis.cover.people.egg-info/requires.txt
seantis.cover.people.egg-info/top_level.txt
seantis/cover/.DS_Store
seantis/cover/__init__.py
seantis/cover/people/__init__.py
seantis/cover/people/configure.zcml
seantis/cover/people/events.zcml
seantis/cover/people/membership.py
seantis/cover/people/profiles.zcml
seantis/cover/people/role.py
seantis/cover/people/setuphandler.py
seantis/cover/people/sync.sh
seantis/cover/people/testing.py
seantis/cover/people/upgrades.zcml
seantis/cover/people/locales/seantis.cover.people.pot
seantis/cover/people/locales/seantis.people.cover.pot
seantis/cover/people/locales/de/LC_MESSAGES/seantis.cover.people.po
seantis/cover/people/locales/de/LC_MESSAGES/seantis.people.cover.po
seantis/cover/people/profiles/default/cssregistry.xml
seantis/cover/people/profiles/default/metadata.xml
seantis/cover/people/profiles/default/registry.xml
seantis/cover/people/profiles/default/seantis.cover.people-default.txt
seantis/cover/people/tests/__init__.py
seantis/cover/people/tests/test_memberships.py
seantis/cover/people/tiles/__init__.py
seantis/cover/people/tiles/configure.zcml
seantis/cover/people/tiles/list.py
seantis/cover/people/tiles/tiles.zcml
seantis/cover/people/tiles/css/base.css
seantis/cover/people/tiles/templates/list.pt