Metadata-Version: 1.1
Name: seantis.cover.people
Version: 0.1
Summary: Integrates collective.cover with seantis.people. 
Home-page: https://github.com/seantis/seantis.cover.people
Author: Seantis GmbH
Author-email: info@seantis.ch
License: GPL v2
Keywords: plone seantis people persons organizations positions
Platform: UNKNOWN
Classifier: Framework :: Plone
Classifier: Framework :: Plone :: 4.3
Classifier: Intended Audience :: Developers
Classifier: Topic :: Software Development :: Libraries :: Python Modules
Classifier: Programming Language :: Python
